{
    "Ar36": {
        "error": 0.00018289599327909626,
        "error_type": "SEM",
        "filter_outliers_dict": {
            "filter_outliers": true,
            "iterations": 1,
            "std_devs": 2,
            "use_iqr_filtering": false,
            "use_standard_deviation_filtering": false
        },
        "fit": "Parabolic",
        "fn": 323,
        "include_baseline_error": true,
        "n": 340,
        "outlier_excluded": [
            323,
            260,
            133,
            168,
            264,
            296,
            299,
            300,
            334,
            48,
            178,
            117,
            187,
            316,
            189,
            222,
            286
        ],
        "reviewed": true,
        "user_excluded": [],
        "value": 0.0031559959562787905
    },
    "Ar37": {
        "error": 0.014555605641979906,
        "error_type": "SEM",
        "filter_outliers_dict": {
            "filter_outliers": true,
            "iterations": 1,
            "std_devs": 2,
            "use_iqr_filtering": false,
            "use_standard_deviation_filtering": false
        },
        "fit": "Linear",
        "fn": 326,
        "include_baseline_error": true,
        "n": 340,
        "outlier_excluded": [
            100,
            70,
            262,
            295,
            327,
            236,
            17,
            211,
            276,
            117,
            53,
            308,
            280,
            189
        ],
        "reviewed": true,
        "user_excluded": [],
        "value": 0.11711441510961401
    },
    "Ar38": {
        "error": 0.004546181289358339,
        "error_type": "SEM",
        "filter_outliers_dict": {
            "filter_outliers": true,
            "iterations": 1,
            "std_devs": 2,
            "use_iqr_filtering": false,
            "use_standard_deviation_filtering": false
        },
        "fit": "Linear",
        "fn": 322,
        "include_baseline_error": true,
        "n": 340,
        "outlier_excluded": [
            160,
            280,
            100,
            136,
            105,
            169,
            171,
            204,
            14,
            16,
            17,
            18,
            211,
            304,
            246,
            119,
            56,
            155
        ],
        "reviewed": true,
        "user_excluded": [],
        "value": 0.09364508661853962
    },
    "Ar39": {
        "error": 0.013046678690517422,
        "error_type": "SEM",
        "filter_outliers_dict": {
            "filter_outliers": true,
            "iterations": 1,
            "std_devs": 2,
            "use_iqr_filtering": false,
            "use_standard_deviation_filtering": false
        },
        "fit": "Parabolic",
        "fn": 326,
        "include_baseline_error": true,
        "n": 340,
        "outlier_excluded": [
            162,
            4,
            293,
            39,
            71,
            168,
            236,
            20,
            84,
            22,
            149,
            315,
            156,
            30
        ],
        "reviewed": true,
        "user_excluded": [],
        "value": -0.004239823924367598
    },
    "Ar40": {
        "error": 0.02500804476543387,
        "error_type": "SEM",
        "filter_outliers_dict": {
            "filter_outliers": true,
            "iterations": 1,
            "std_devs": 2,
            "use_iqr_filtering": false,
            "use_standard_deviation_filtering": false
        },
        "fit": "Parabolic",
        "fn": 324,
        "include_baseline_error": true,
        "n": 340,
        "outlier_excluded": [
            261,
            166,
            137,
            139,
            76,
            270,
            16,
            51,
            211,
            118,
            214,
            312,
            90,
            123,
            124,
            317
        ],
        "reviewed": true,
        "user_excluded": [],
        "value": 0.29676957546182337
    }
}